MANIFEST.in
NEWS.txt
README.rst
setup.py
src/cascajal/__init__.py
src/cascajal/cli.py
src/cascajal/profile.py
src/cascajal.egg-info/PKG-INFO
src/cascajal.egg-info/SOURCES.txt
src/cascajal.egg-info/dependency_links.txt
src/cascajal.egg-info/entry_points.txt
src/cascajal.egg-info/top_level.txt
src/cascajal.egg-info/zip-safe
src/cascajal/data/extensions.ini
src/cascajal/data/prefs.js
src/cascajal/data/prontoprint/README.md
src/cascajal/data/prontoprint/package.json
src/cascajal/data/prontoprint/prontoprint.xpi
src/cascajal/data/prontoprint/doc/main.md
src/cascajal/data/prontoprint/lib/main.js
src/cascajal/data/prontoprint/test/test-main.js
src/cascajal/tests/__init__.py
src/cascajal/tests/profile_tests.py