Metadata-Version: 1.1
Name: cascajal
Version: 0.1
Summary: PDF generation for Hieroglyph presentations.
Home-page: https://github.com/nyergler/cascajal
Author: Nathan R. Yergler
Author-email: nathan@yergler.net
License: BSD
Keywords: PDF presentation text-processing
Platform: UNKNOWN
Classifier: License :: OSI Approved :: BSD License
Classifier: Topic :: Documentation
Classifier: Topic :: Text Processing
Classifier: Programming Language :: Python :: 2
Classifier: Programming Language :: Python :: 3
